starplot/__init__.py
starplot/base.py
starplot/callables.py
starplot/cli.py
starplot/config.py
starplot/coordinates.py
starplot/geod.py
starplot/geometry.py
starplot/horizon.py
starplot/map.py
starplot/mixins.py
starplot/optic.py
starplot/profile.py
starplot/projections.py
starplot/utils.py
starplot/warnings.py
starplot/zenith.py
starplot/data/__init__.py
starplot/data/catalogs.py
starplot/data/constellations.py
starplot/data/db.py
starplot/data/dsos.py
starplot/data/ecliptic.py
starplot/data/stars.py
starplot/data/translations.py
starplot/data/utils.py
starplot/data/library/constellation_names.parquet
starplot/data/library/dso_names.parquet
starplot/data/library/readme.md
starplot/data/library/sky.db
starplot/data/library/star_designations.parquet
starplot/models/__init__.py
starplot/models/base.py
starplot/models/comet.py
starplot/models/constellation.py
starplot/models/dso.py
starplot/models/moon.py
starplot/models/objects.py
starplot/models/observer.py
starplot/models/optics.py
starplot/models/planet.py
starplot/models/satellite.py
starplot/models/star.py
starplot/models/sun.py
starplot/plotters/__init__.py
starplot/plotters/arrow.py
starplot/plotters/constellations.py
starplot/plotters/dsos.py
starplot/plotters/experimental.py
starplot/plotters/gradients.py
starplot/plotters/legend.py
starplot/plotters/milkyway.py
starplot/plotters/stars.py
starplot/styles/__init__.py
starplot/styles/base.py
starplot/styles/extensions.py
starplot/styles/fonts.py
starplot/styles/helpers.py
starplot/styles/markers.py
starplot/styles/ext/antique.yml
starplot/styles/ext/blue_dark.yml
starplot/styles/ext/blue_gold.yml
starplot/styles/ext/blue_light.yml
starplot/styles/ext/blue_medium.yml
starplot/styles/ext/blue_night.yml
starplot/styles/ext/cb_wong.yml
starplot/styles/ext/color_print.yml
starplot/styles/ext/gradient_presets.yml
starplot/styles/ext/grayscale.yml
starplot/styles/ext/grayscale_dark.yml
starplot/styles/ext/map.yml
starplot/styles/ext/nord.yml
starplot-0.18.2.dist-info/entry_points.txt
starplot-0.18.2.dist-info/licenses/LICENSE
starplot-0.18.2.dist-info/WHEEL
starplot-0.18.2.dist-info/METADATA
starplot-0.18.2.dist-info/RECORD
