Metadata-Version: 2.4
Name: starplot
Version: 0.18.2
Summary: Star charts and maps of the sky
Keywords: astronomy,stars,charts,maps,constellations,sky,plotting
Author-email: Steve Berardi <hello@steveberardi.com>
Classifier: License :: OSI Approved :: MIT License
Classifier: Programming Language :: Python :: 3
Classifier: Programming Language :: Python :: 3.10
Classifier: Programming Language :: Python :: 3.11
Classifier: Programming Language :: Python :: 3.12
Classifier: Programming Language :: Python :: 3.13
License-File: LICENSE
Requires-Dist: matplotlib >= 3.8.0
Requires-Dist: numpy >= 1.26.2
Requires-Dist: pandas >= 1.4.0
Requires-Dist: pydantic >= 2.10.6
Requires-Dist: shapely >= 2.0.1
Requires-Dist: skyfield >= 1.41
Requires-Dist: cartopy >= 0.21.1
Requires-Dist: geopandas >= 1.0.1
Requires-Dist: pillow >= 10.0.0
Requires-Dist: PyYAML >= 6.0.1
Requires-Dist: pyarrow >= 14.0.2
Requires-Dist: pyogrio >= 0.10.0
Requires-Dist: rtree >= 1.2.0
Requires-Dist: requests >= 2.31.0
Requires-Dist: duckdb < 1.4.0
Requires-Dist: ibis-framework[duckdb, geospatial] < 11
Requires-Dist: astropy-healpix >= 1.1.2
Project-URL: Documentation, https://starplot.dev
Project-URL: Home, https://starplot.dev
Project-URL: Source, https://github.com/steveberardi/starplot
